{
  "날짜": "2022년 05월 14일 20:00",
  "리스트": [
    {
      "id": 1,
      "name": "NONE",
      "MonetaryUnit": "====선택====",
      "현찰사실때": "0",
      "현찰파실때": "0",
      "송금_전신환보내실때": "0",
      "송금_전신환받으실때": "0",
      "Criteria": "0",
      "Sign": ""
    },
    {
      "id": 2,
      "name": "USD",
      "MonetaryUnit": "미국 USD",
      "현찰사실때": "1306.47",
      "현찰파실때": "1261.53",
      "송금_전신환보내실때": "1296.50",
      "송금_전신환받으실때": "1271.50",
      "Criteria": "1284.00",
      "Sign": "$"
    },
    {
      "id": 3,
      "name": "JPY",
      "MonetaryUnit": "일본 JPY 100",
      "현찰사실때": "1012.88",
      "현찰파실때": "978.04",
      "송금_전신환보내실때": "1005.21",
      "송금_전신환받으실때": "985.71",
      "Criteria": "995.46",
      "Sign": "¥"
    },
    {
      "id": 4,
      "name": "EUR",
      "MonetaryUnit": "유로 EUR",
      "현찰사실때": "1360.36",
      "현찰파실때": "1307.28",
      "송금_전신환보내실때": "1347.15",
      "송금_전신환받으실때": "1320.49",
      "Criteria": "1333.82",
      "Sign": "€"
    },
    {
      "id": 6,
      "name": "CNY",
      "MonetaryUnit": "중국 CNY",
      "현찰사실때": "198.08",
      "현찰파실때": "179.22",
      "송금_전신환보내실때": "190.53",
      "송금_전신환받으실때": "186.77",
      "Criteria": "188.65",
      "Sign": "¥"
    },
    {
      "id": 7,
      "name": "HKD",
      "MonetaryUnit": "홍콩 HKD",
      "현찰사실때": "166.79",
      "현찰파실때": "160.35",
      "송금_전신환보내실때": "165.20",
      "송금_전신환받으실때": "161.94",
      "Criteria": "163.57",
      "Sign": "$"
    },
    {
      "id": 8,
      "name": "THB",
      "MonetaryUnit": "태국 THB",
      "현찰사실때": "38.75",
      "현찰파실때": "34.70",
      "송금_전신환보내실때": "37.27",
      "송금_전신환받으실때": "36.55",
      "Criteria": "36.91",
      "Sign": "฿"
    },
    {
      "id": 9,
      "name": "TWD",
      "MonetaryUnit": "대만 TWD",
      "현찰사실때": "48.65",
      "현찰파실때": "40.01",
      "송금_전신환보내실때": "0.00",
      "송금_전신환받으실때": "0.00",
      "Criteria": "43.02",
      "Sign": "$"
    },
    {
      "id": 10,
      "name": "PHP",
      "MonetaryUnit": "필리핀 PHP",
      "현찰사실때": "26.93",
      "현찰파실때": "22.49",
      "송금_전신환보내실때": "24.73",
      "송금_전신환받으실때": "24.25",
      "Criteria": "24.49",
      "Sign": "₱"
    },
    {
      "id": 11,
      "name": "SGD",
      "MonetaryUnit": "싱가포르 SGD",
      "현찰사실때": "938.17",
      "현찰파실때": "901.57",
      "송금_전신환보내실때": "929.06",
      "송금_전신환받으실때": "910.68",
      "Criteria": "919.87",
      "Sign": "$"
    },
    {
      "id": 12,
      "name": "AUD",
      "MonetaryUnit": "호주 AUD",
      "현찰사실때": "902.03",
      "현찰파실때": "867.19",
      "송금_전신환보내실때": "893.45",
      "송금_전신환받으실때": "875.77",
      "Criteria": "884.61",
      "Sign": "$"
    },
    {
      "id": 13,
      "name": "VND",
      "MonetaryUnit": "베트남 VND 100",
      "현찰사실때": "6.21",
      "현찰파실때": "4.91",
      "송금_전신환보내실때": "5.61",
      "송금_전신환받으실때": "5.51",
      "Criteria": "5.56",
      "Sign": "₫"
    },
    {
      "id": 14,
      "name": "GBP",
      "MonetaryUnit": "영국 GBP",
      "현찰사실때": "1597.47",
      "현찰파실때": "1535.75",
      "송금_전신환보내실때": "1582.27",
      "송금_전신환받으실때": "1550.95",
      "Criteria": "1566.61",
      "Sign": "£"
    },
    {
      "id": 15,
      "name": "CAD",
      "MonetaryUnit": "캐나다 CAD",
      "현찰사실때": "1007.07",
      "현찰파실때": "968.17",
      "송금_전신환보내실때": "997.49",
      "송금_전신환받으실때": "977.75",
      "Criteria": "987.62",
      "Sign": "$"
    },
    {
      "id": 16,
      "name": "MYR",
      "MonetaryUnit": "말레이시아 MYR",
      "현찰사실때": "310.34",
      "현찰파실때": "270.35",
      "송금_전신환보내실때": "0.00",
      "송금_전신환받으실때": "289.04",
      "Criteria": "291.95",
      "Sign": "RM"
    },
    {
      "id": 17,
      "name": "RUB",
      "MonetaryUnit": "러시아 RUB",
      "현찰사실때": "21.59",
      "현찰파실때": "16.27",
      "송금_전신환보내실때": "20.41",
      "송금_전신환받으실때": "19.03",
      "Criteria": "19.72",
      "Sign": "р."
    },
    {
      "id": 18,
      "name": "ZAR",
      "MonetaryUnit": "남아공화국 ZAR",
      "현찰사실때": "84.54",
      "현찰파실때": "73.38",
      "송금_전신환보내실때": "80.71",
      "송금_전신환받으실때": "78.81",
      "Criteria": "79.76",
      "Sign": "R"
    },
    {
      "id": 19,
      "name": "NOK",
      "MonetaryUnit": "노르웨이 NOK",
      "현찰사실때": "134.04",
      "현찰파실때": "127.64",
      "송금_전신환보내실때": "132.14",
      "송금_전신환받으실때": "129.54",
      "Criteria": "130.84",
      "Sign": "kr"
    },
    {
      "id": 20,
      "name": "NZD",
      "MonetaryUnit": "뉴질랜드 NZD",
      "현찰사실때": "817.71",
      "현찰파실때": "786.13",
      "송금_전신환보내실때": "809.93",
      "송금_전신환받으실때": "793.91",
      "Criteria": "801.92",
      "Sign": "$"
    },
    {
      "id": 21,
      "name": "DKK",
      "MonetaryUnit": "덴마크 DKK",
      "현찰사실때": "183.65",
      "현찰파실때": "174.87",
      "송금_전신환보내실때": "181.05",
      "송금_전신환받으실때": "177.47",
      "Criteria": "179.26",
      "Sign": "kr"
    },
    {
      "id": 22,
      "name": "MXN",
      "MonetaryUnit": "멕시코 MXN",
      "현찰사실때": "69.94",
      "현찰파실때": "58.25",
      "송금_전신환보내실때": "64.22",
      "송금_전신환받으실때": "62.96",
      "Criteria": "63.59",
      "Sign": "$"
    },
    {
      "id": 23,
      "name": "MNT",
      "MonetaryUnit": "몽골 MNT",
      "현찰사실때": "0.00",
      "현찰파실때": "0.00",
      "송금_전신환보내실때": "0.00",
      "송금_전신환받으실때": "0.00",
      "Criteria": "0.41",
      "Sign": "₮"
    },
    {
      "id": 24,
      "name": "BHD",
      "MonetaryUnit": "바레인 BHD",
      "현찰사실때": "3624.10",
      "현찰파실때": "3133.63",
      "송금_전신환보내실때": "3440.17",
      "송금_전신환받으실때": "3372.05",
      "Criteria": "3406.11",
      "Sign": "ب.د"
    },
    {
      "id": 25,
      "name": "BDT",
      "MonetaryUnit": "방글라데시 BDT",
      "현찰사실때": "0.00",
      "현찰파실때": "0.00",
      "송금_전신환보내실때": "0.00",
      "송금_전신환받으실때": "0.00",
      "Criteria": "14.81",
      "Sign": "৳"
    },
    {
      "id": 26,
      "name": "BRL",
      "MonetaryUnit": "브라질 BRL",
      "현찰사실때": "275.56",
      "현찰파실때": "230.06",
      "송금_전신환보내실때": "0.00",
      "송금_전신환받으실때": "247.06",
      "Criteria": "250.06",
      "Sign": "R$"
    },
    {
      "id": 27,
      "name": "BND",
      "MonetaryUnit": "브루나이 BND",
      "현찰사실때": "956.66",
      "현찰파실때": "864.68",
      "송금_전신환보내실때": "0.00",
      "송금_전신환받으실때": "0.00",
      "Criteria": "919.87",
      "Sign": "$"
    },
    {
      "id": 28,
      "name": "SAR",
      "MonetaryUnit": "사우디아라비아 SAR",
      "현찰사실때": "363.87",
      "현찰파실때": "318.70",
      "송금_전신환보내실때": "345.73",
      "송금_전신환받으실때": "338.89",
      "Criteria": "342.31",
      "Sign": "ر.س"
    },
    {
      "id": 29,
      "name": "LKR",
      "MonetaryUnit": "스리랑카 LKR",
      "현찰사실때": "0.00",
      "현찰파실때": "0.00",
      "송금_전신환보내실때": "0.00",
      "송금_전신환받으실때": "0.00",
      "Criteria": "3.57",
      "Sign": "Rs"
    },
    {
      "id": 30,
      "name": "SEK",
      "MonetaryUnit": "스웨덴 SEK",
      "현찰사실때": "130.19",
      "현찰파실때": "123.97",
      "송금_전신환보내실때": "128.35",
      "송금_전신환받으실때": "125.81",
      "Criteria": "127.08",
      "Sign": "kr"
    },
    {
      "id": 31,
      "name": "CHF",
      "MonetaryUnit": "스위스 CHF",
      "현찰사실때": "1309.75",
      "현찰파실때": "1259.15",
      "송금_전신환보내실때": "1297.29",
      "송금_전신환받으실때": "1271.61",
      "Criteria": "1284.45",
      "Sign": "₣"
    },
    {
      "id": 32,
      "name": "AED",
      "MonetaryUnit": "아랍에미리트공화국 AED",
      "현찰사실때": "368.79",
      "현찰파실때": "325.45",
      "송금_전신환보내실때": "353.06",
      "송금_전신환받으실때": "346.08",
      "Criteria": "349.57",
      "Sign": "د.إ"
    },
    {
      "id": 33,
      "name": "DZD",
      "MonetaryUnit": "알제리 DZD",
      "현찰사실때": "0.00",
      "현찰파실때": "0.00",
      "송금_전신환보내실때": "0.00",
      "송금_전신환받으실때": "0.00",
      "Criteria": "8.77",
      "Sign": "د.ج"
    },
    {
      "id": 34,
      "name": "OMR",
      "MonetaryUnit": "오만 OMR",
      "현찰사실때": "3631.97",
      "현찰파실때": "3135.05",
      "송금_전신환보내실때": "0.00",
      "송금_전신환받으실때": "0.00",
      "Criteria": "3335.15",
      "Sign": "ر.ع."
    },
    {
      "id": 35,
      "name": "JOD",
      "MonetaryUnit": "요르단 JOD",
      "현찰사실때": "1972.17",
      "현찰파실때": "1666.12",
      "송금_전신환보내실때": "0.00",
      "송금_전신환받으실때": "0.00",
      "Criteria": "1811.00",
      "Sign": "د.ا"
    },
    {
      "id": 36,
      "name": "ILS",
      "MonetaryUnit": "이스라엘 ILS",
      "현찰사실때": "412.58",
      "현찰파실때": "345.08",
      "송금_전신환보내실때": "0.00",
      "송금_전신환받으실때": "0.00",
      "Criteria": "375.08",
      "Sign": "₪"
    },
    {
      "id": 37,
      "name": "EGP",
      "MonetaryUnit": "이집트 EGP",
      "현찰사실때": "0.00",
      "현찰파실때": "0.00",
      "송금_전신환보내실때": "0.00",
      "송금_전신환받으실때": "0.00",
      "Criteria": "70.11",
      "Sign": "£"
    },
    {
      "id": 38,
      "name": "INR",
      "MonetaryUnit": "인도 INR",
      "현찰사실때": "0.00",
      "현찰파실때": "0.00",
      "송금_전신환보내실때": "0.00",
      "송금_전신환받으실때": "0.00",
      "Criteria": "16.57",
      "Sign": "₹"
    },
    {
      "id": 39,
      "name": "IDR",
      "MonetaryUnit": "인도네시아 IDR 100",
      "현찰사실때": "9.42",
      "현찰파실때": "7.93",
      "송금_전신환보내실때": "8.89",
      "송금_전신환받으실때": "8.73",
      "Criteria": "8.81",
      "Sign": "₹"
    },
    {
      "id": 40,
      "name": "CZK",
      "MonetaryUnit": "체코 CZK",
      "현찰사실때": "58.44",
      "현찰파실때": "49.03",
      "송금_전신환보내실때": "54.46",
      "송금_전신환받으실때": "53.28",
      "Criteria": "53.87",
      "Sign": "Kč"
    },
    {
      "id": 41,
      "name": "CLP",
      "MonetaryUnit": "칠레 CLP",
      "현찰사실때": "1.59",
      "현찰파실때": "1.37",
      "송금_전신환보내실때": "0.00",
      "송금_전신환받으실때": "0.00",
      "Criteria": "1.48",
      "Sign": "$"
    },
    {
      "id": 42,
      "name": "KZT",
      "MonetaryUnit": "카자흐스탄 KZT",
      "현찰사실때": "0.00",
      "현찰파실때": "0.00",
      "송금_전신환보내실때": "0.00",
      "송금_전신환받으실때": "0.00",
      "Criteria": "2.97",
      "Sign": "〒"
    },
    {
      "id": 43,
      "name": "QAR",
      "MonetaryUnit": "카타르 QAR",
      "현찰사실때": "0.00",
      "현찰파실때": "0.00",
      "송금_전신환보내실때": "0.00",
      "송금_전신환받으실때": "0.00",
      "Criteria": "352.14",
      "Sign": "ر.ق"
    },
    {
      "id": 44,
      "name": "KES",
      "MonetaryUnit": "케냐 KES",
      "현찰사실때": "0.00",
      "현찰파실때": "0.00",
      "송금_전신환보내실때": "0.00",
      "송금_전신환받으실때": "0.00",
      "Criteria": "11.05",
      "Sign": "Sh"
    },
    {
      "id": 45,
      "name": "COP",
      "MonetaryUnit": "콜롬비아 COP",
      "현찰사실때": "0.00",
      "현찰파실때": "0.00",
      "송금_전신환보내실때": "0.00",
      "송금_전신환받으실때": "0.00",
      "Criteria": "0.31",
      "Sign": "$"
    },
    {
      "id": 46,
      "name": "KWD",
      "MonetaryUnit": "쿠웨이트 KWD",
      "현찰사실때": "4454.99",
      "현찰파실때": "3848.45",
      "송금_전신환보내실때": "4224.92",
      "송금_전신환받으실때": "4141.26",
      "Criteria": "4183.09",
      "Sign": "د.ك"
    },
    {
      "id": 47,
      "name": "TZS",
      "MonetaryUnit": "탄자니아 TZS",
      "현찰사실때": "0.00",
      "현찰파실때": "0.00",
      "송금_전신환보내실때": "0.00",
      "송금_전신환받으실때": "0.00",
      "Criteria": "0.55",
      "Sign": "Sh"
    },
    {
      "id": 48,
      "name": "TRY",
      "MonetaryUnit": "터키 TRY",
      "현찰사실때": "0.00",
      "현찰파실때": "0.00",
      "송금_전신환보내실때": "83.87",
      "송금_전신환받으실때": "82.05",
      "Criteria": "82.96",
      "Sign": "₤"
    },
    {
      "id": 49,
      "name": "PKR",
      "MonetaryUnit": "파키스탄 PKR",
      "현찰사실때": "0.00",
      "현찰파실때": "0.00",
      "송금_전신환보내실때": "0.00",
      "송금_전신환받으실때": "0.00",
      "Criteria": "6.64",
      "Sign": "₨"
    },
    {
      "id": 50,
      "name": "PLN",
      "MonetaryUnit": "폴란드 PLN",
      "현찰사실때": "308.26",
      "현찰파실때": "262.60",
      "송금_전신환보내실때": "288.56",
      "송금_전신환받으실때": "282.30",
      "Criteria": "285.43",
      "Sign": "zł"
    },
    {
      "id": 51,
      "name": "HUF",
      "MonetaryUnit": "헝가리 HUF",
      "현찰사실때": "3.79",
      "현찰파실때": "3.20",
      "송금_전신환보내실때": "3.50",
      "송금_전신환받으실때": "3.44",
      "Criteria": "3.47",
      "Sign": "Ft"
    }
  ]
}
